geoopt/__init__.py
geoopt/docutils.py
geoopt/tensor.py
geoopt/utils.py
geoopt/datasets/__init__.py
geoopt/datasets/stereographic.py
geoopt/layers/__init__.py
geoopt/layers/stereographic.py
geoopt/linalg/__init__.py
geoopt/linalg/batch_linalg.py
geoopt/manifolds/__init__.py
geoopt/manifolds/base.py
geoopt/manifolds/birkhoff_polytope.py
geoopt/manifolds/euclidean.py
geoopt/manifolds/product.py
geoopt/manifolds/scaled.py
geoopt/manifolds/sphere.py
geoopt/manifolds/stiefel.py
geoopt/manifolds/symmetric_positive_definite.py
geoopt/manifolds/lorentz/__init__.py
geoopt/manifolds/lorentz/math.py
geoopt/manifolds/siegel/__init__.py
geoopt/manifolds/siegel/bounded_domain.py
geoopt/manifolds/siegel/csym_math.py
geoopt/manifolds/siegel/siegel.py
geoopt/manifolds/siegel/upper_half.py
geoopt/manifolds/siegel/vvd_metrics.py
geoopt/manifolds/stereographic/__init__.py
geoopt/manifolds/stereographic/manifold.py
geoopt/manifolds/stereographic/math.py
geoopt/optim/__init__.py
geoopt/optim/mixin.py
geoopt/optim/radam.py
geoopt/optim/rlinesearch.py
geoopt/optim/rsgd.py
geoopt/optim/sparse_radam.py
geoopt/optim/sparse_rsgd.py
geoopt/samplers/__init__.py
geoopt/samplers/base.py
geoopt/samplers/rhmc.py
geoopt/samplers/rsgld.py
geoopt/samplers/sgrhmc.py
geoopt-0.5.1.dist-info/licenses/LICENSE
geoopt-0.5.1.dist-info/WHEEL
geoopt-0.5.1.dist-info/METADATA
geoopt-0.5.1.dist-info/RECORD
