Metadata-Version: 2.4
Name: geoopt
Version: 0.5.1
Summary: Unofficial implementation for “Riemannian Adaptive Optimization Methods” ICLR2019 and more
Author-email: Geoopt Developers <maxim.v.kochurov@gmail.com>
Requires-Python: >=3.8
Classifier: Development Status :: 2 - Pre-Alpha
Classifier: Programming Language :: Python
Classifier: Programming Language :: Python :: 3
Classifier: Programming Language :: Python :: 3.6
Classifier: License :: OSI Approved :: Apache Software License
Classifier: Intended Audience :: Science/Research
Classifier: Topic :: Scientific/Engineering
Classifier: Topic :: Scientific/Engineering :: Mathematics
Classifier: Operating System :: OS Independent
License-File: LICENSE
Requires-Dist: torch>=2.0.1
Requires-Dist: numpy
Requires-Dist: scipy
Requires-Dist: pytest ; extra == "dev"
Requires-Dist: pytest-cov ; extra == "dev"
Requires-Dist: pytest-html ; extra == "dev"
Requires-Dist: black ; extra == "dev"
Requires-Dist: coveralls ; extra == "dev"
Requires-Dist: twine ; extra == "dev"
Requires-Dist: wheel ; extra == "dev"
Requires-Dist: seaborn ; extra == "dev"
Requires-Dist: pydocstyle>=6.3.0 ; extra == "dev"
Requires-Dist: pylint ; extra == "dev"
Requires-Dist: sphinx ; extra == "dev"
Requires-Dist: matplotlib ; extra == "rtd"
Project-URL: documentation, https://geoopt.readthedocs.io/en/latest/
Project-URL: homepage, https://github.com/geoopt/geoopt
Project-URL: repository, https://github.com/geoopt/geoopt
Provides-Extra: dev
Provides-Extra: rtd
